twitterxauth
