Metadata-Version: 1.0
Name: twitterxauth
Version: 0.0.3dev
Summary: thin wrapper module for xAuth twitter.com
Home-page: UNKNOWN
Author: yuitest
Author-email: yuitest+git@cjhat.net
License: UNKNOWN
Keywords: twitter xauth
Platform: UNKNOWN
